[
  {
    "verifyText": {
      "id": "lf_title_label",
      "value": "Should I lease or own my business location?"
    }
  },
  {
    "click": {
      "id": "lf-LeaseOption-tab-label"
    }
  },
  {
    "setTextAndWait": {
      "id": "lf_Business_CRELeaseSecurityDeposit",
      "value": "2,800"
    }
  },
  {
    "select": {
      "id": "lf_Business_IsCRELeaseSecurityDepositRefundable",
      "value": "label=Yes"
    }
  },
  {
    "setTextAndWait": {
      "id": "lf_Business_CRELeaseTerm",
      "value": "48"
    }
  },
  {
    "select": {
      "id": "lf_Business_CRELeasePaymentType",
      "value": "label=Per square foot"
    }
  },
  {
    "select": {
      "id": "lf_Business_CRELeasePaymentType",
      "value": "label=Flat rate"
    }
  },
  {
    "setTextAndWait": {
      "id": "lf_Business_CRELeaseFlatRatePayment",
      "value": "2,500"
    }
  },
  {
    "setTextAndWait": {
      "id": "lf_Business_AnnualIncreaseInLeasePayments",
      "value": "2.555"
    }
  },
  {
    "setTextAndWait": {
      "id": "lf_Business_OtherLeaseFees",
      "value": "300"
    }
  },
  {
    "click": {
      "id": "lf-BuyOption-tab-label"
    }
  },
  {
    "setTextAndWait": {
      "id": "lf_Business_CREPurchasePrice",
      "value": "150,000"
    }
  },
  {
    "setTextAndWait": {
      "id": "lf_Business_CREPurchasePricePortionForLand",
      "value": "35,000"
    }
  },
  {
    "setTextAndWait": {
      "id": "lf_Business_CREClosingCosts",
      "value": "4,500"
    }
  },
  {
    "setTextAndWait": {
      "id": "lf_Business_CREDownPaymentPercentage",
      "value": "15.00"
    }
  },
  {
    "setTextAndWait": {
      "id": "lf_Business_CRELoanTerm",
      "value": "360"
    }
  },
  {
    "setTextAndWait": {
      "id": "lf_Business_CREInterestRate",
      "value": "5.450"
    }
  },
  {
    "select": {
      "id": "lf_Business_CREMACRSDepreciationYears",
      "value": "label=27"
    }
  },
  {
    "click": {
      "id": "lf-Expenses-tab-label"
    }
  },
  {
    "setTextAndWait": {
      "id": "lf_Business_CRELeaseConstructionCosts",
      "value": "0"
    }
  },
  {
    "setTextAndWait": {
      "id": "lf_Business_CRELoanConstructionCosts",
      "value": "25,000"
    }
  },
  {
    "setTextAndWait": {
      "id": "lf_Business_CRELeaseAnnualPropertyInsurance",
      "value": "0"
    }
  },
  {
    "setTextAndWait": {
      "id": "lf_Business_CRELoanAnnualPropertyInsurance",
      "value": "1,300"
    }
  },
  {
    "setTextAndWait": {
      "id": "lf_Business_CRELoanAnnualPropertyTax",
      "value": "5,600"
    }
  },
  {
    "setTextAndWait": {
      "id": "lf_Business_CRELeaseMonthlyMaintenance",
      "value": "80"
    }
  },
  {
    "setTextAndWait": {
      "id": "lf_Business_CRELoanMonthlyMaintenance",
      "value": "500"
    }
  },
  {
    "setTextAndWait": {
      "id": "lf_Business_CRELeaseMonthlyElectricity",
      "value": "300"
    }
  },
  {
    "setTextAndWait": {
      "id": "lf_Business_CRELoanMonthlyElectricity",
      "value": "300"
    }
  },
  {
    "setTextAndWait": {
      "id": "lf_Business_CRELeaseMonthlyGas",
      "value": "150"
    }
  },
  {
    "setTextAndWait": {
      "id": "lf_Business_CRELoanMonthlyGas",
      "value": "150"
    }
  },
  {
    "setTextAndWait": {
      "id": "lf_Business_CRELeaseMonthlySewer",
      "value": "60"
    }
  },
  {
    "setTextAndWait": {
      "id": "lf_Business_CRELoanMonthlySewer",
      "value": "60"
    }
  },
  {
    "setTextAndWait": {
      "id": "lf_Business_CRELeaseMonthlyWasteDisposal",
      "value": "50"
    }
  },
  {
    "setTextAndWait": {
      "id": "lf_Business_CRELoanMonthlyWasteDisposal",
      "value": "50"
    }
  },
  {
    "setTextAndWait": {
      "id": "lf_Business_CRELeaseMonthlyWater",
      "value": "150"
    }
  },
  {
    "setTextAndWait": {
      "id": "lf_Business_CRELeaseMonthlyOtherCosts",
      "value": "100"
    }
  },
  {
    "setTextAndWait": {
      "id": "lf_Business_CRELoanMonthlyOtherCosts",
      "value": "100"
    }
  },
  {
    "click": {
      "id": "lf-Property-tab-label"
    }
  },
  {
    "setTextAndWait": {
      "id": "lf_Business_CRESquareFootageDesired",
      "value": "2,500"
    }
  },
  {
    "select": {
      "id": "lf_Business_PredictedYearlyChangeInPropertyValues",
      "value": "label=Increase"
    }
  },
  {
    "setTextAndWait": {
      "id": "lf_Business_PredictedYearlyChangeAmountInPropertyValues",
      "value": "3.550"
    }
  },
  {
    "click": {
      "id": "lf-TaxesInflation-tab-label"
    }
  },
  {
    "setTextAndWait": {
      "id": "lf_Business_FederalTaxRate",
      "value": "32.15"
    }
  },
  {
    "setTextAndWait": {
      "id": "lf_Business_StateTaxRate",
      "value": "6.45"
    }
  },
  {
    "setTextAndWait": {
      "id": "lf_Business_SavingsRate",
      "value": "2.55"
    }
  },
  {
    "setTextAndWait": {
      "id": "lf_Global_InflationRate",
      "value": "2.55"
    }
  },
  {
    "setTextAndWait": {
      "id": "lf_Global_InflationRate",
      "value": "2.55"
    }
  },
  {
    "click": {
      "id": "lf-results-tab-label"
    }
  },
  {
    "waitForText": {
      "id": "lf_answer",
      "value": "Buying will cost you, in today's dollars, $74,572 less than leasing over 48 months"
    }
  },
  {
    "click": {
      "id": "lf_answer_more_info"
    }
  },
  {
    "verifyText": {
      "id": "lf_LeaseNPVNetPmts_result_label",
      "value": "Total cost, in today's dollars over 48 months"
    }
  },
  {
    "verifyText": {
      "id": "lf_LeaseNPVNetPmts_result_value",
      "value": "$175,234"
    }
  },
  {
    "verifyText": {
      "id": "lf_LoanNPVNetPmts_result_value",
      "value": "$100,662"
    }
  },
  {
    "click": {
      "id": "lf_answer_more_info"
    }
  }
]